ipypencil/__init__.py
ipypencil/_frontend.py
ipypencil/_version.py
ipypencil/canvas.py
ipypencil/labextension/package.json
ipypencil/labextension/static/122.5853e5e282be73b20912.js
ipypencil/labextension/static/509.80bd8e3f19d059dd1932.js
ipypencil/labextension/static/885.aecfd66711d222e5ac44.js
ipypencil/labextension/static/remoteEntry.e271264e8fd31b986363.js
ipypencil/labextension/static/style.js
ipypencil/labextension/static/third-party-licenses.json
ipypencil/nbextension/extension.js
ipypencil/nbextension/index.js
ipypencil/nbextension/index.js.map
ipypencil/tests/__init__.py
ipypencil/tests/conftest.py
ipypencil/tests/test_example.py
ipypencil/tests/test_nbextension_path.py
ipypencil-0.1.1.data/data/share/jupyter/labextensions/jupyter-pencil/package.json
ipypencil-0.1.1.data/data/share/jupyter/labextensions/jupyter-pencil/static/122.5853e5e282be73b20912.js
ipypencil-0.1.1.data/data/share/jupyter/labextensions/jupyter-pencil/static/509.80bd8e3f19d059dd1932.js
ipypencil-0.1.1.data/data/share/jupyter/labextensions/jupyter-pencil/static/885.aecfd66711d222e5ac44.js
ipypencil-0.1.1.data/data/share/jupyter/labextensions/jupyter-pencil/static/remoteEntry.e271264e8fd31b986363.js
ipypencil-0.1.1.data/data/share/jupyter/labextensions/jupyter-pencil/static/style.js
ipypencil-0.1.1.data/data/share/jupyter/labextensions/jupyter-pencil/static/third-party-licenses.json
ipypencil-0.1.1.data/data/share/jupyter/nbextensions/ipypencil/extension.js
ipypencil-0.1.1.data/data/share/jupyter/nbextensions/ipypencil/index.js
ipypencil-0.1.1.data/data/share/jupyter/nbextensions/ipypencil/index.js.map
ipypencil-0.1.1.data/data/etc/jupyter/nbconfig/notebook.d/ipypencil.json
ipypencil-0.1.1.data/data/share/jupyter/labextensions/jupyter-pencil/install.json
ipypencil-0.1.1.dist-info/METADATA
ipypencil-0.1.1.dist-info/WHEEL
ipypencil-0.1.1.dist-info/licenses/LICENSE.txt
ipypencil-0.1.1.dist-info/RECORD
